commondata/__init__.py
commondata/countries.py
commondata/peppolcodes.py
commondata/utils.py
commondata/demonames/african.py
commondata/demonames/bel.py
commondata/demonames/est.py
commondata/demonames/french.py
commondata/demonames/muslim.py
commondata/demonames/russian.py
commondata/demonames/streets.py
commondata/demonames/ury.py
commondata/places/estonia.py
commondata-25.2.0.dist-info/METADATA
commondata-25.2.0.dist-info/WHEEL
commondata-25.2.0.dist-info/licenses/COPYING
commondata-25.2.0.dist-info/RECORD
