Metadata-Version: 2.4
Name: commondata
Version: 25.2.0
Summary: Share structured common data in a pythonic way
Project-URL: Homepage, https://dev.lino-framework.org/topics/commondata.html
Project-URL: Repository, https://github.com/lsaffre/commondata
Author-email: Rumma & Ko Ltd <info@saffre-rumma.net>, Luc Saffre <luc@lino-framework.org>
License:                     GNU AFFERO GENERAL PUBLIC LICENSE
License-File: COPYING
Classifier: Development Status :: 5 - Production/Stable
Classifier: Intended Audience :: Developers
Classifier: License :: OSI Approved :: GNU Affero General Public License v3
Classifier: Natural Language :: English
Classifier: Operating System :: OS Independent
Classifier: Programming Language :: Python
Classifier: Programming Language :: Python :: 3
Requires-Dist: click
Requires-Dist: requests
